<?xml version="1.0" encoding="UTF-8"?>
<beans xmlns="http://www.springframework.org/schema/beans" xmlns:xsi="http://www.w3.org/2001/XMLSchema-instance"
    xsi:schemaLocation="http://www.springframework.org/schema/beans http://www.springframework.org/schema/beans/spring-beans-4.0.xsd">

    <!-- 프로퍼티 정보 설정 -->
    <bean name="propertiesService" class="egovframework.rte.fdl.property.impl.EgovPropertyServiceImpl" destroy-method="destroy">
        <property name="properties">
            <map>
                <entry key="pageUnit" value="10"/>
                <entry key="pageSize" value="10"/>
                <entry key="posblAtchFileSize" value="5242880"/>
                <entry key="Globals.fileStorePath" value="/kicpa/portal/kicpa/upload"/>
                <entry key="Globals.addedOptions" value="false"/>
                <entry key="inicisMid" value="kicpaorkr6"/> <!--kicpaorkr6  kicpaorkr7 INIpayTest-->
                <entry key="inicisHashKey" value="3CB8183A4BE283555ACC8363C0360223"/>
            </map>
        </property>
    </bean>
</beans>
